bso/__init__.py
bso/client.py
bso/models.py
bso-2.0.0.dist-info/METADATA
bso-2.0.0.dist-info/WHEEL
bso-2.0.0.dist-info/top_level.txt
bso-2.0.0.dist-info/RECORD
